pp/__init__.py
pp/__main__.py
pp/_pp.py
pp/auto.py
pp/common.py
pp/transport.py
pp/worker.py
pp/server/__init__.py
pp/server/__main__.py
ppft/__info__.py
ppft/__init__.py
ppft/__main__.py
ppft/_pp.py
ppft/auto.py
ppft/common.py
ppft/transport.py
ppft/worker.py
ppft/server/__init__.py
ppft/server/__main__.py
ppft/tests/__init__.py
ppft/tests/__main__.py
ppft/tests/auto_diff.py
ppft/tests/callback.py
ppft/tests/dynamic_ncpus.py
ppft/tests/quicksort.py
ppft/tests/reverse_md5.py
ppft/tests/sum_primes.py
ppft/tests/sum_primes_functor.py
ppft-1.7.6.9.data/scripts/ppserver
ppft-1.7.6.9.dist-info/COPYING
ppft-1.7.6.9.dist-info/LICENSE
ppft-1.7.6.9.dist-info/METADATA
ppft-1.7.6.9.dist-info/WHEEL
ppft-1.7.6.9.dist-info/top_level.txt
ppft-1.7.6.9.dist-info/RECORD
