Metadata-Version: 2.1
Name: ppft
Version: 1.7.6.9
Summary: distributed and parallel Python
Home-page: https://github.com/uqfoundation/ppft
Download-URL: https://pypi.org/project/ppft/#files
Author: Mike McKerns
Author-email: mmckerns@uqfoundation.org
Maintainer: Mike McKerns
Maintainer-email: mmckerns@uqfoundation.org
License: BSD-3-Clause
Project-URL: Documentation, http://ppft.rtfd.io
Project-URL: Source Code, https://github.com/uqfoundation/ppft
Project-URL: Bug Tracker, https://github.com/uqfoundation/ppft/issues
Platform: Linux
Platform: Windows
Platform: Mac
Classifier: Development Status :: 5 - Production/Stable
Classifier: Intended Audience :: Developers
Classifier: Intended Audience :: Science/Research
Classifier: License :: OSI Approved :: BSD License
Classifier: Programming Language :: Python :: 3
Classifier: Programming Language :: Python :: 3.8
Classifier: Programming Language :: Python :: 3.9
Classifier: Programming Language :: Python :: 3.10
Classifier: Programming Language :: Python :: 3.11
Classifier: Programming Language :: Python :: 3.12
Classifier: Programming Language :: Python :: 3.13
Classifier: Programming Language :: Python :: Implementation :: CPython
Classifier: Programming Language :: Python :: Implementation :: PyPy
Classifier: Topic :: Scientific/Engineering
Classifier: Topic :: Software Development
Requires-Python: >=3.8
License-File: LICENSE
License-File: COPYING
Provides-Extra: dill
Requires-Dist: dill>=0.3.9; extra == "dill"
